trytond/modules/health_stock_inpatient/COPYING
trytond/modules/health_stock_inpatient/MANIFEST.in
trytond/modules/health_stock_inpatient/README.rst
trytond/modules/health_stock_inpatient/__init__.py
trytond/modules/health_stock_inpatient/data/messages/messages.xml
trytond/modules/health_stock_inpatient/doc/index.rst
trytond/modules/health_stock_inpatient/exceptions.py
trytond/modules/health_stock_inpatient/health_stock_inpatient.py
trytond/modules/health_stock_inpatient/health_stock_inpatient_view.xml
trytond/modules/health_stock_inpatient/locale/ar.po
trytond/modules/health_stock_inpatient/locale/de.po
trytond/modules/health_stock_inpatient/locale/el.po
trytond/modules/health_stock_inpatient/locale/eo.po
trytond/modules/health_stock_inpatient/locale/es.po
trytond/modules/health_stock_inpatient/locale/fr.po
trytond/modules/health_stock_inpatient/locale/health_stock_inpatient.pot
trytond/modules/health_stock_inpatient/locale/it_IT.po
trytond/modules/health_stock_inpatient/locale/ja_JP.po
trytond/modules/health_stock_inpatient/locale/ka.po
trytond/modules/health_stock_inpatient/locale/lo.po
trytond/modules/health_stock_inpatient/locale/pt_BR.po
trytond/modules/health_stock_inpatient/locale/sv.po
trytond/modules/health_stock_inpatient/locale/tr.po
trytond/modules/health_stock_inpatient/locale/uk.po
trytond/modules/health_stock_inpatient/locale/zh_CN.po
trytond/modules/health_stock_inpatient/pyproject.toml
trytond/modules/health_stock_inpatient/tests/__init__.py
trytond/modules/health_stock_inpatient/tests/test_health_stock_inpatient.py
trytond/modules/health_stock_inpatient/tryton.cfg
trytond/modules/health_stock_inpatient/view/gnuhealth_patient_rounding.xml
trytond/modules/health_stock_inpatient/view/gnuhealth_patient_rounding_tree.xml
trytond/modules/health_stock_inpatient/view/gnuhealth_rounding_medical_supply_tree.xml
trytond/modules/health_stock_inpatient/view/gnuhealth_rounding_medicament_form.xml
gnuhealth_stock_inpatient-5.0.2.dist-info/METADATA
gnuhealth_stock_inpatient-5.0.2.dist-info/WHEEL
gnuhealth_stock_inpatient-5.0.2.dist-info/licenses/COPYING
gnuhealth_stock_inpatient-5.0.2.dist-info/RECORD
